MenuBuilder_pkg/__init__.py
MenuBuilder-1.2.dist-info/METADATA
MenuBuilder-1.2.dist-info/WHEEL
MenuBuilder-1.2.dist-info/top_level.txt
MenuBuilder-1.2.dist-info/RECORD
