Metadata-Version: 2.1
Name: MenuBuilder
Version: 1.2
Summary: A simple commandline menu builder
Home-page: https://github.com/OOgaboogaboog/MenuBuilder
Author: Ewen
Author-email: 1lorimerewe2@gmail.com
License: UNKNOWN
Platform: UNKNOWN
Classifier: Programming Language :: Python :: 3
Classifier: License :: OSI Approved :: MIT License
Classifier: Operating System :: OS Independent
Requires-Python: <=3.9
